w3storage/__init__.py
w3storage-0.0.1.dist-info/LICENSE
w3storage-0.0.1.dist-info/METADATA
w3storage-0.0.1.dist-info/WHEEL
w3storage-0.0.1.dist-info/top_level.txt
w3storage-0.0.1.dist-info/RECORD
