Metadata-Version: 2.1
Name: w3storage
Version: 0.0.1
Summary: A Python client for https://web3.storage
Home-page: https://github.com/xloem/py-w3storage
License: GPLv2+
Classifier: License :: OSI Approved :: GNU General Public License v2 or later (GPLv2+)
Classifier: Natural Language :: English
Classifier: Programming Language :: Python :: 3
License-File: LICENSE
Requires-Dist: requests
